{
    "tl_news": {
        "headline": [
            "Title",
            "Please enter the news title."
        ],
        "alias": [
            "News alias",
            "The news alias is a unique reference to the news item which can be called instead of its numeric ID."
        ],
        "author": [
            "Author",
            "Here you can change the author of the news item."
        ],
        "date": [
            "Date",
            "Please enter the date according to the global date format."
        ],
        "time": [
            "Time",
            "Please enter the time according to the global time format."
        ],
        "pageTitle": [
            "Meta title",
            "Here you can add a custom meta title to overwrite the default page title."
        ],
        "description": [
            "Meta description",
            "Here you can add a custom meta description to overwrite the default page description."
        ],
        "subheadline": [
            "Subheadline",
            "Here you can enter a subheadline."
        ],
        "teaser": [
            "News teaser",
            "The news teaser can be shown in a news list instead of the full story. A \"read more …\" link will be added automatically."
        ],
        "text": [
            "News text",
            "Here you can enter the news text."
        ],
        "addImage": [
            "Add an image",
            "Add an image to the news item."
        ],
        "addEnclosure": [
            "Add enclosures",
            "Add one or more downloadable files to the news item."
        ],
        "enclosure": [
            "Enclosures",
            "Please choose the files you want to attach."
        ],
        "source": [
            "Redirect target",
            "Here you can override the default redirect target."
        ],
        "default": [
            "Use default",
            "By clicking the \"read more …\" button, visitors will be redirected to the default page of the news archive."
        ],
        "internal": [
            "Page",
            "By clicking the \"read more …\" button, visitors will be redirected to a page."
        ],
        "article": [
            "Article",
            "By clicking the \"read more …\" button, visitors will be redirected to an article."
        ],
        "external": [
            "Custom URL",
            "By clicking the \"read more …\" button, visitors will be redirected to a custom URL."
        ],
        "jumpTo": [
            "Redirect page",
            "Please choose the page to which visitors will be redirected when clicking the news item."
        ],
        "articleId": [
            "Article",
            "Please choose the article to which visitors will be redirected when clicking the news item."
        ],
        "cssClass": [
            "CSS class",
            "Here you can enter one or more classes."
        ],
        "noComments": [
            "Disable comments",
            "Do not allow comments for this particular news item."
        ],
        "featured": [
            "Feature item",
            "Show the news item in a featured news list."
        ],
        "published": [
            "Publish item",
            "Make the news item publicly visible on the website."
        ],
        "start": [
            "Show from",
            "Do not show the news item on the website before this day."
        ],
        "stop": [
            "Show until",
            "Do not show the news item on the website on and after this day."
        ],
        "tstamp": [
            "Revision date",
            "Date and time of the latest revision"
        ],
        "title_legend": "Title and author",
        "date_legend": "Date and time",
        "meta_legend": "Meta data",
        "teaser_legend": "Subheadline and teaser",
        "text_legend": "News text",
        "image_legend": "Image settings",
        "enclosure_legend": "Enclosures",
        "source_legend": "Redirect target",
        "expert_legend": "Expert settings",
        "publish_legend": "Publish settings",
        "new": [
            "New item",
            "Create a new news item"
        ],
        "show": [
            "Item details",
            "Show the details of news item ID %s"
        ],
        "edit": [
            "Edit item",
            "Edit news item ID %s"
        ],
        "copy": [
            "Duplicate item",
            "Duplicate news item ID %s"
        ],
        "cut": [
            "Move item",
            "Move news item ID %s"
        ],
        "delete": [
            "Delete item",
            "Delete news item ID %s"
        ],
        "toggle": [
            "Publish/unpublish item",
            "Publish/unpublish news item ID %s"
        ],
        "feature": [
            "Feature/unfeature item",
            "Feature/unfeature news item ID %s"
        ],
        "editheader": [
            "Edit archive",
            "Edit the news archive settings"
        ],
        "editmeta": [
            "Edit item settings",
            "Edit the news item settings"
        ],
        "pasteafter": [
            "Paste into this news archive",
            "Paste after news item ID %s"
        ],
        "languageMain": [
            "Master article",
            "Choose the article in the master archive equaling this article."
        ],
        "sameDay": "Same day",
        "otherDay": "Other days"
    },
    "MOD": {
        "content": "Content",
        "article": [
            "Articles",
            "Manage articles and content elements"
        ],
        "form": [
            "Form generator",
            "Create custom forms and store or send the submitted data"
        ],
        "design": "Layout",
        "themes": [
            "Themes",
            "Manage front end modules, style sheets, page layouts and templates"
        ],
        "page": [
            "Site structure",
            "Set up the site structure of your website(s)"
        ],
        "tpl_editor": [
            "Templates",
            "Edit templates in the back end"
        ],
        "accounts": "Account manager",
        "member": [
            "Members",
            "Manage member accounts (front end users)"
        ],
        "mgroup": [
            "Member groups",
            "Manage member groups (front end user groups)"
        ],
        "user": [
            "Users",
            "Manage user accounts (back end users)"
        ],
        "group": [
            "User groups",
            "Manage user groups (back end user groups)"
        ],
        "opt_in": [
            "Double opt-in",
            "Manage the double opt-in tokens"
        ],
        "system": "System",
        "files": [
            "File manager",
            "Manage files and folders or upload new files to the server"
        ],
        "log": [
            "System log",
            "Browse the system log and analyze the activity on the website"
        ],
        "settings": [
            "Settings",
            "Check and optimize the Contao configuration"
        ],
        "maintenance": [
            "Maintenance",
            "Maintain or update Contao"
        ],
        "security": [
            "Security",
            "Secure your account"
        ],
        "undo": [
            "Restore",
            "Restore deleted records"
        ],
        "login": [
            "User profile",
            "Change your personal data or set a new password"
        ],
        "tl_content": "Content elements",
        "tl_form_field": "Fields",
        "tl_image_size": "Image sizes",
        "tl_image_size_item": "Media queries",
        "tl_layout": "Page layouts",
        "tl_module": "Front end modules",
        "tl_style": "Format definitions",
        "tl_style_sheet": "Style sheets",
        "css": "Style sheets",
        "modules": "Front end modules",
        "layout": "Page layouts",
        "image_sizes": "Image sizes",
        "theme_import": "Theme import",
        "theme_export": "Theme export",
        "listing": [
            "Listing",
            "List the records of any table"
        ],
        "news": [
            "News",
            "Manage news and export them as RSS or Atom feed"
        ],
        "tl_news_feed": "News feeds",
        "tl_news": "Articles",
        "changelanguage": [
            "Change Language"
        ]
    },
    "FMD": {
        "navigationMenu": "Navigation",
        "navigation": [
            "Navigation menu",
            "Generates a navigation menu from the site structure"
        ],
        "customnav": [
            "Custom navigation",
            "Generates a custom navigation menu"
        ],
        "breadcrumb": [
            "Breadcrumb navigation",
            "Generates a breadcrumb navigation menu"
        ],
        "quicknav": [
            "Quick navigation",
            "Generates a drop-down menu from the site structure"
        ],
        "quicklink": [
            "Quick link",
            "Generates a custom drop-down menu"
        ],
        "booknav": [
            "Book navigation",
            "Generates a book navigation menu"
        ],
        "articlenav": [
            "Article navigation",
            "Generates a pagination menu to navigate articles"
        ],
        "sitemap": [
            "Sitemap",
            "Generates a list of all pages in the site structure"
        ],
        "user": "User",
        "login": [
            "Login form",
            "Generates a login form"
        ],
        "logout": [
            "Automatic logout",
            "Automatically logs out a user"
        ],
        "personalData": [
            "Personal data",
            "Generates a form to edit a user's personal data"
        ],
        "registration": [
            "Registration",
            "Generates a user registration form"
        ],
        "changePassword": [
            "Change password",
            "Generates a form to change the password"
        ],
        "lostPassword": [
            "Lost password",
            "Generates a form to request a new password"
        ],
        "closeAccount": [
            "Close account",
            "Generates a form to delete a member account"
        ],
        "application": "Applications",
        "form": [
            "Form",
            "Adds a form to the page"
        ],
        "search": [
            "Search engine",
            "Adds a search form to the page"
        ],
        "articlelist": [
            "Article list",
            "Generates a list of articles of a column"
        ],
        "miscellaneous": "Miscellaneous",
        "randomImage": [
            "Random image",
            "Adds a random image to the page"
        ],
        "html": [
            "Custom HTML",
            "Allows you to add custom HTML code"
        ],
        "rssReader": [
            "RSS reader",
            "Adds an RSS feed to the page"
        ],
        "listing": [
            "Listing",
            "Lists the records of any table"
        ],
        "news": "News",
        "newslist": [
            "Newslist",
            "Adds a list of news items to the page"
        ],
        "newsreader": [
            "Newsreader",
            "Shows the details of a news item"
        ],
        "newsarchive": [
            "News archive",
            "Adds a news archive to the page"
        ],
        "newsmenu": [
            "News archive menu",
            "Generates a navigation menu to browse the news archive"
        ],
        "changelanguage": [
            "Change Language",
            "This module allows you to switch between different language versions of a page."
        ]
    }
}